[{"Natureza":"HOMIC\u00cdDIO DOLOSO (2)","Janeiro":1,"Fevereiro":0,"Marco":0,"Abril":0,"Maio":1,"Junho":0,"Julho":0,"Agosto":1,"Setembro":1,"Outubro":0,"Novembro":0,"Dezembro":1,"Total":5.0},{"Natureza":"N\u00ba DE V\u00cdTIMAS EM HOMIC\u00cdDIO DOLOSO (3)","Janeiro":1,"Fevereiro":0,"Marco":0,"Abril":0,"Maio":1,"Junho":0,"Julho":0,"Agosto":1,"Setembro":1,"Outubro":0,"Novembro":0,"Dezembro":1,"Total":5.0},{"Natureza":"HOMIC\u00cdDIO DOLOSO POR ACIDENTE DE TR\u00c2NSITO","Janeiro":1,"Fevereiro":0,"Marco":0,"Abril":0,"Maio":0,"Junho":0,"Julho":0,"Agosto":0,"Setembro":0,"Outubro":0,"Novembro":0,"Dezembro":0,"Total":1.0},{"Natureza":"N\u00ba DE V\u00cdTIMAS EM HOMIC\u00cdDIO DOLOSO POR ACIDENTE DE TR\u00c2NSITO","Janeiro":1,"Fevereiro":0,"Marco":0,"Abril":0,"Maio":0,"Junho":0,"Julho":0,"Agosto":0,"Setembro":0,"Outubro":0,"Novembro":0,"Dezembro":0,"Total":1.0},{"Natureza":"HOMIC\u00cdDIO CULPOSO POR ACIDENTE DE TR\u00c2NSITO","Janeiro":0,"Fevereiro":0,"Marco":0,"Abril":0,"Maio":0,"Junho":0,"Julho":0,"Agosto":0,"Setembro":1,"Outubro":1,"Novembro":0,"Dezembro":0,"Total":2.0},{"Natureza":"HOMIC\u00cdDIO CULPOSO OUTROS","Janeiro":0,"Fevereiro":0,"Marco":0,"Abril":0,"Maio":0,"Junho":0,"Julho":0,"Agosto":0,"Setembro":0,"Outubro":0,"Novembro":0,"Dezembro":0,"Total":0.0},{"Natureza":"TENTATIVA DE HOMIC\u00cdDIO","Janeiro":0,"Fevereiro":1,"Marco":0,"Abril":0,"Maio":1,"Junho":0,"Julho":0,"Agosto":0,"Setembro":1,"Outubro":0,"Novembro":0,"Dezembro":0,"Total":3.0},{"Natureza":"LES\u00c3O CORPORAL SEGUIDA DE MORTE","Janeiro":0,"Fevereiro":0,"Marco":0,"Abril":0,"Maio":0,"Junho":0,"Julho":0,"Agosto":0,"Setembro":0,"Outubro":0,"Novembro":0,"Dezembro":0,"Total":0.0},{"Natureza":"LES\u00c3O CORPORAL DOLOSA","Janeiro":16,"Fevereiro":18,"Marco":10,"Abril":12,"Maio":5,"Junho":14,"Julho":18,"Agosto":19,"Setembro":19,"Outubro":20,"Novembro":12,"Dezembro":14,"Total":177.0},{"Natureza":"LES\u00c3O CORPORAL CULPOSA POR ACIDENTE DE TR\u00c2NSITO","Janeiro":23,"Fevereiro":15,"Marco":24,"Abril":11,"Maio":17,"Junho":23,"Julho":17,"Agosto":17,"Setembro":10,"Outubro":12,"Novembro":12,"Dezembro":16,"Total":197.0},{"Natureza":"LES\u00c3O CORPORAL CULPOSA - OUTRAS","Janeiro":2,"Fevereiro":0,"Marco":1,"Abril":1,"Maio":2,"Junho":0,"Julho":0,"Agosto":1,"Setembro":0,"Outubro":1,"Novembro":1,"Dezembro":0,"Total":9.0},{"Natureza":"LATROC\u00cdNIO","Janeiro":0,"Fevereiro":0,"Marco":0,"Abril":0,"Maio":0,"Junho":0,"Julho":0,"Agosto":0,"Setembro":0,"Outubro":0,"Novembro":0,"Dezembro":0,"Total":0.0},{"Natureza":"N\u00ba DE V\u00cdTIMAS EM LATROC\u00cdNIO","Janeiro":0,"Fevereiro":0,"Marco":0,"Abril":0,"Maio":0,"Junho":0,"Julho":0,"Agosto":0,"Setembro":0,"Outubro":0,"Novembro":0,"Dezembro":0,"Total":0.0},{"Natureza":"TOTAL DE ESTUPRO (4)","Janeiro":4,"Fevereiro":1,"Marco":2,"Abril":0,"Maio":0,"Junho":3,"Julho":2,"Agosto":2,"Setembro":0,"Outubro":0,"Novembro":2,"Dezembro":0,"Total":16.0},{"Natureza":"ESTUPRO","Janeiro":1,"Fevereiro":0,"Marco":1,"Abril":0,"Maio":0,"Junho":1,"Julho":0,"Agosto":0,"Setembro":0,"Outubro":0,"Novembro":1,"Dezembro":0,"Total":4.0},{"Natureza":"ESTUPRO DE VULNER\u00c1VEL","Janeiro":3,"Fevereiro":1,"Marco":1,"Abril":0,"Maio":0,"Junho":2,"Julho":2,"Agosto":2,"Setembro":0,"Outubro":0,"Novembro":1,"Dezembro":0,"Total":12.0},{"Natureza":"TOTAL DE ROUBO - OUTROS (1)","Janeiro":123,"Fevereiro":130,"Marco":84,"Abril":58,"Maio":70,"Junho":127,"Julho":104,"Agosto":94,"Setembro":82,"Outubro":91,"Novembro":127,"Dezembro":134,"Total":1.224},{"Natureza":"ROUBO - OUTROS","Janeiro":121,"Fevereiro":129,"Marco":82,"Abril":55,"Maio":68,"Junho":127,"Julho":104,"Agosto":94,"Setembro":81,"Outubro":91,"Novembro":127,"Dezembro":132,"Total":1.211},{"Natureza":"ROUBO DE VE\u00cdCULO","Janeiro":15,"Fevereiro":18,"Marco":21,"Abril":14,"Maio":12,"Junho":6,"Julho":15,"Agosto":34,"Setembro":9,"Outubro":7,"Novembro":12,"Dezembro":24,"Total":187.0},{"Natureza":"ROUBO A BANCO","Janeiro":0,"Fevereiro":0,"Marco":0,"Abril":0,"Maio":0,"Junho":0,"Julho":0,"Agosto":0,"Setembro":0,"Outubro":0,"Novembro":0,"Dezembro":0,"Total":0.0},{"Natureza":"ROUBO DE CARGA","Janeiro":2,"Fevereiro":1,"Marco":2,"Abril":3,"Maio":2,"Junho":0,"Julho":0,"Agosto":0,"Setembro":1,"Outubro":0,"Novembro":0,"Dezembro":2,"Total":13.0},{"Natureza":"FURTO - OUTROS","Janeiro":135,"Fevereiro":146,"Marco":120,"Abril":61,"Maio":78,"Junho":140,"Julho":111,"Agosto":109,"Setembro":101,"Outubro":123,"Novembro":127,"Dezembro":125,"Total":1.376},{"Natureza":"FURTO DE VE\u00cdCULO","Janeiro":27,"Fevereiro":18,"Marco":24,"Abril":11,"Maio":17,"Junho":23,"Julho":13,"Agosto":16,"Setembro":23,"Outubro":25,"Novembro":34,"Dezembro":16,"Total":247.0}]