[{"Natureza":"HOMIC\u00cdDIO DOLOSO (2)","Janeiro":3,"Fevereiro":0,"Marco":0,"Abril":0,"Maio":0,"Junho":1,"Julho":1,"Agosto":0,"Setembro":0,"Outubro":0,"Novembro":0,"Dezembro":0,"Total":5.0},{"Natureza":"N\u00ba DE V\u00cdTIMAS EM HOMIC\u00cdDIO DOLOSO (3)","Janeiro":3,"Fevereiro":0,"Marco":0,"Abril":0,"Maio":0,"Junho":2,"Julho":1,"Agosto":0,"Setembro":0,"Outubro":0,"Novembro":0,"Dezembro":0,"Total":6.0},{"Natureza":"HOMIC\u00cdDIO DOLOSO POR ACIDENTE DE TR\u00c2NSITO","Janeiro":0,"Fevereiro":0,"Marco":0,"Abril":0,"Maio":0,"Junho":0,"Julho":0,"Agosto":0,"Setembro":0,"Outubro":0,"Novembro":0,"Dezembro":0,"Total":0.0},{"Natureza":"N\u00ba DE V\u00cdTIMAS EM HOMIC\u00cdDIO DOLOSO POR ACIDENTE DE TR\u00c2NSITO","Janeiro":0,"Fevereiro":0,"Marco":0,"Abril":0,"Maio":0,"Junho":0,"Julho":0,"Agosto":0,"Setembro":0,"Outubro":0,"Novembro":0,"Dezembro":0,"Total":0.0},{"Natureza":"HOMIC\u00cdDIO CULPOSO POR ACIDENTE DE TR\u00c2NSITO","Janeiro":0,"Fevereiro":0,"Marco":0,"Abril":1,"Maio":0,"Junho":0,"Julho":0,"Agosto":0,"Setembro":0,"Outubro":2,"Novembro":0,"Dezembro":1,"Total":4.0},{"Natureza":"HOMIC\u00cdDIO CULPOSO OUTROS","Janeiro":0,"Fevereiro":0,"Marco":0,"Abril":0,"Maio":0,"Junho":0,"Julho":0,"Agosto":0,"Setembro":0,"Outubro":0,"Novembro":0,"Dezembro":0,"Total":0.0},{"Natureza":"TENTATIVA DE HOMIC\u00cdDIO","Janeiro":0,"Fevereiro":0,"Marco":0,"Abril":0,"Maio":0,"Junho":2,"Julho":1,"Agosto":0,"Setembro":1,"Outubro":1,"Novembro":2,"Dezembro":2,"Total":9.0},{"Natureza":"LES\u00c3O CORPORAL SEGUIDA DE MORTE","Janeiro":0,"Fevereiro":0,"Marco":0,"Abril":0,"Maio":0,"Junho":0,"Julho":0,"Agosto":0,"Setembro":0,"Outubro":0,"Novembro":0,"Dezembro":0,"Total":0.0},{"Natureza":"LES\u00c3O CORPORAL DOLOSA","Janeiro":30,"Fevereiro":22,"Marco":29,"Abril":29,"Maio":29,"Junho":25,"Julho":30,"Agosto":21,"Setembro":20,"Outubro":25,"Novembro":30,"Dezembro":24,"Total":314.0},{"Natureza":"LES\u00c3O CORPORAL CULPOSA POR ACIDENTE DE TR\u00c2NSITO","Janeiro":19,"Fevereiro":18,"Marco":28,"Abril":22,"Maio":37,"Junho":17,"Julho":25,"Agosto":26,"Setembro":21,"Outubro":28,"Novembro":19,"Dezembro":26,"Total":286.0},{"Natureza":"LES\u00c3O CORPORAL CULPOSA - OUTRAS","Janeiro":2,"Fevereiro":0,"Marco":3,"Abril":2,"Maio":0,"Junho":0,"Julho":2,"Agosto":1,"Setembro":0,"Outubro":0,"Novembro":0,"Dezembro":2,"Total":12.0},{"Natureza":"LATROC\u00cdNIO","Janeiro":0,"Fevereiro":0,"Marco":0,"Abril":0,"Maio":0,"Junho":0,"Julho":0,"Agosto":0,"Setembro":0,"Outubro":0,"Novembro":0,"Dezembro":0,"Total":0.0},{"Natureza":"N\u00ba DE V\u00cdTIMAS EM LATROC\u00cdNIO","Janeiro":0,"Fevereiro":0,"Marco":0,"Abril":0,"Maio":0,"Junho":0,"Julho":0,"Agosto":0,"Setembro":0,"Outubro":0,"Novembro":0,"Dezembro":0,"Total":0.0},{"Natureza":"TOTAL DE ESTUPRO (4)","Janeiro":3,"Fevereiro":1,"Marco":4,"Abril":0,"Maio":2,"Junho":3,"Julho":2,"Agosto":2,"Setembro":3,"Outubro":2,"Novembro":2,"Dezembro":3,"Total":27.0},{"Natureza":"ESTUPRO","Janeiro":1,"Fevereiro":1,"Marco":4,"Abril":0,"Maio":1,"Junho":1,"Julho":2,"Agosto":1,"Setembro":2,"Outubro":0,"Novembro":2,"Dezembro":2,"Total":17.0},{"Natureza":"ESTUPRO DE VULNER\u00c1VEL","Janeiro":2,"Fevereiro":0,"Marco":0,"Abril":0,"Maio":1,"Junho":2,"Julho":0,"Agosto":1,"Setembro":1,"Outubro":2,"Novembro":0,"Dezembro":1,"Total":10.0},{"Natureza":"TOTAL DE ROUBO - OUTROS (1)","Janeiro":159,"Fevereiro":138,"Marco":194,"Abril":160,"Maio":314,"Junho":247,"Julho":203,"Agosto":198,"Setembro":203,"Outubro":227,"Novembro":231,"Dezembro":177,"Total":2.451},{"Natureza":"ROUBO - OUTROS","Janeiro":157,"Fevereiro":136,"Marco":189,"Abril":159,"Maio":311,"Junho":246,"Julho":203,"Agosto":196,"Setembro":202,"Outubro":226,"Novembro":227,"Dezembro":176,"Total":2.428},{"Natureza":"ROUBO DE VE\u00cdCULO","Janeiro":12,"Fevereiro":20,"Marco":21,"Abril":16,"Maio":31,"Junho":21,"Julho":18,"Agosto":17,"Setembro":18,"Outubro":13,"Novembro":21,"Dezembro":16,"Total":224.0},{"Natureza":"ROUBO A BANCO","Janeiro":0,"Fevereiro":0,"Marco":1,"Abril":0,"Maio":1,"Junho":0,"Julho":0,"Agosto":0,"Setembro":0,"Outubro":0,"Novembro":0,"Dezembro":0,"Total":2.0},{"Natureza":"ROUBO DE CARGA","Janeiro":2,"Fevereiro":2,"Marco":4,"Abril":1,"Maio":2,"Junho":1,"Julho":0,"Agosto":2,"Setembro":1,"Outubro":1,"Novembro":4,"Dezembro":1,"Total":21.0},{"Natureza":"FURTO - OUTROS","Janeiro":312,"Fevereiro":255,"Marco":332,"Abril":380,"Maio":485,"Junho":282,"Julho":320,"Agosto":335,"Setembro":173,"Outubro":432,"Novembro":374,"Dezembro":386,"Total":4.066},{"Natureza":"FURTO DE VE\u00cdCULO","Janeiro":51,"Fevereiro":92,"Marco":60,"Abril":57,"Maio":99,"Junho":55,"Julho":62,"Agosto":77,"Setembro":104,"Outubro":86,"Novembro":56,"Dezembro":35,"Total":834.0}]