[{"Natureza":"HOMIC\u00cdDIO DOLOSO (2)","Janeiro":0,"Fevereiro":0,"Marco":2,"Abril":0,"Maio":1,"Junho":1,"Julho":"...","Agosto":"...","Setembro":"...","Outubro":"...","Novembro":"...","Dezembro":"...","Total":4},{"Natureza":"N\u00ba DE V\u00cdTIMAS EM HOMIC\u00cdDIO DOLOSO (3)","Janeiro":0,"Fevereiro":0,"Marco":2,"Abril":0,"Maio":1,"Junho":1,"Julho":"...","Agosto":"...","Setembro":"...","Outubro":"...","Novembro":"...","Dezembro":"...","Total":4},{"Natureza":"HOMIC\u00cdDIO DOLOSO POR ACIDENTE DE TR\u00c2NSITO","Janeiro":0,"Fevereiro":0,"Marco":0,"Abril":0,"Maio":0,"Junho":0,"Julho":"...","Agosto":"...","Setembro":"...","Outubro":"...","Novembro":"...","Dezembro":"...","Total":0},{"Natureza":"N\u00ba DE V\u00cdTIMAS EM HOMIC\u00cdDIO DOLOSO POR ACIDENTE DE TR\u00c2NSITO","Janeiro":0,"Fevereiro":0,"Marco":0,"Abril":0,"Maio":0,"Junho":0,"Julho":"...","Agosto":"...","Setembro":"...","Outubro":"...","Novembro":"...","Dezembro":"...","Total":0},{"Natureza":"HOMIC\u00cdDIO CULPOSO POR ACIDENTE DE TR\u00c2NSITO","Janeiro":1,"Fevereiro":1,"Marco":1,"Abril":1,"Maio":0,"Junho":1,"Julho":"...","Agosto":"...","Setembro":"...","Outubro":"...","Novembro":"...","Dezembro":"...","Total":5},{"Natureza":"HOMIC\u00cdDIO CULPOSO OUTROS","Janeiro":0,"Fevereiro":0,"Marco":0,"Abril":0,"Maio":1,"Junho":0,"Julho":"...","Agosto":"...","Setembro":"...","Outubro":"...","Novembro":"...","Dezembro":"...","Total":1},{"Natureza":"TENTATIVA DE HOMIC\u00cdDIO","Janeiro":1,"Fevereiro":2,"Marco":2,"Abril":1,"Maio":1,"Junho":1,"Julho":"...","Agosto":"...","Setembro":"...","Outubro":"...","Novembro":"...","Dezembro":"...","Total":8},{"Natureza":"LES\u00c3O CORPORAL SEGUIDA DE MORTE","Janeiro":0,"Fevereiro":0,"Marco":0,"Abril":0,"Maio":0,"Junho":0,"Julho":"...","Agosto":"...","Setembro":"...","Outubro":"...","Novembro":"...","Dezembro":"...","Total":0},{"Natureza":"LES\u00c3O CORPORAL DOLOSA","Janeiro":33,"Fevereiro":35,"Marco":34,"Abril":39,"Maio":27,"Junho":34,"Julho":"...","Agosto":"...","Setembro":"...","Outubro":"...","Novembro":"...","Dezembro":"...","Total":202},{"Natureza":"LES\u00c3O CORPORAL CULPOSA POR ACIDENTE DE TR\u00c2NSITO","Janeiro":2,"Fevereiro":5,"Marco":8,"Abril":11,"Maio":16,"Junho":8,"Julho":"...","Agosto":"...","Setembro":"...","Outubro":"...","Novembro":"...","Dezembro":"...","Total":50},{"Natureza":"LES\u00c3O CORPORAL CULPOSA - OUTRAS","Janeiro":0,"Fevereiro":1,"Marco":0,"Abril":1,"Maio":0,"Junho":1,"Julho":"...","Agosto":"...","Setembro":"...","Outubro":"...","Novembro":"...","Dezembro":"...","Total":3},{"Natureza":"LATROC\u00cdNIO","Janeiro":0,"Fevereiro":1,"Marco":0,"Abril":0,"Maio":0,"Junho":0,"Julho":"...","Agosto":"...","Setembro":"...","Outubro":"...","Novembro":"...","Dezembro":"...","Total":1},{"Natureza":"N\u00ba DE V\u00cdTIMAS EM LATROC\u00cdNIO","Janeiro":0,"Fevereiro":1,"Marco":0,"Abril":0,"Maio":0,"Junho":0,"Julho":"...","Agosto":"...","Setembro":"...","Outubro":"...","Novembro":"...","Dezembro":"...","Total":1},{"Natureza":"TOTAL DE ESTUPRO (4)","Janeiro":3,"Fevereiro":1,"Marco":3,"Abril":2,"Maio":2,"Junho":8,"Julho":"...","Agosto":"...","Setembro":"...","Outubro":"...","Novembro":"...","Dezembro":"...","Total":19},{"Natureza":"ESTUPRO","Janeiro":2,"Fevereiro":1,"Marco":0,"Abril":0,"Maio":0,"Junho":2,"Julho":"...","Agosto":"...","Setembro":"...","Outubro":"...","Novembro":"...","Dezembro":"...","Total":5},{"Natureza":"ESTUPRO DE VULNER\u00c1VEL","Janeiro":1,"Fevereiro":0,"Marco":3,"Abril":2,"Maio":2,"Junho":6,"Julho":"...","Agosto":"...","Setembro":"...","Outubro":"...","Novembro":"...","Dezembro":"...","Total":14},{"Natureza":"TOTAL DE ROUBO - OUTROS (1)","Janeiro":80,"Fevereiro":71,"Marco":74,"Abril":85,"Maio":61,"Junho":89,"Julho":"...","Agosto":"...","Setembro":"...","Outubro":"...","Novembro":"...","Dezembro":"...","Total":460},{"Natureza":"ROUBO - OUTROS","Janeiro":76,"Fevereiro":68,"Marco":73,"Abril":83,"Maio":60,"Junho":87,"Julho":"...","Agosto":"...","Setembro":"...","Outubro":"...","Novembro":"...","Dezembro":"...","Total":447},{"Natureza":"ROUBO DE VE\u00cdCULO","Janeiro":17,"Fevereiro":9,"Marco":18,"Abril":28,"Maio":16,"Junho":22,"Julho":"...","Agosto":"...","Setembro":"...","Outubro":"...","Novembro":"...","Dezembro":"...","Total":110},{"Natureza":"ROUBO A BANCO","Janeiro":0,"Fevereiro":0,"Marco":0,"Abril":0,"Maio":0,"Junho":0,"Julho":"...","Agosto":"...","Setembro":"...","Outubro":"...","Novembro":"...","Dezembro":"...","Total":0},{"Natureza":"ROUBO DE CARGA","Janeiro":4,"Fevereiro":3,"Marco":1,"Abril":2,"Maio":1,"Junho":2,"Julho":"...","Agosto":"...","Setembro":"...","Outubro":"...","Novembro":"...","Dezembro":"...","Total":13},{"Natureza":"FURTO - OUTROS","Janeiro":95,"Fevereiro":77,"Marco":84,"Abril":75,"Maio":108,"Junho":93,"Julho":"...","Agosto":"...","Setembro":"...","Outubro":"...","Novembro":"...","Dezembro":"...","Total":532},{"Natureza":"FURTO DE VE\u00cdCULO","Janeiro":27,"Fevereiro":40,"Marco":22,"Abril":22,"Maio":43,"Junho":35,"Julho":"...","Agosto":"...","Setembro":"...","Outubro":"...","Novembro":"...","Dezembro":"...","Total":189}]