[{"Natureza":"HOMIC\u00cdDIO DOLOSO (2)","Janeiro":2,"Fevereiro":4,"Marco":2,"Abril":1,"Maio":0,"Junho":0,"Julho":0,"Agosto":3,"Setembro":1,"Outubro":1,"Novembro":0,"Dezembro":1,"Total":15},{"Natureza":"N\u00ba DE V\u00cdTIMAS EM HOMIC\u00cdDIO DOLOSO (3)","Janeiro":2,"Fevereiro":4,"Marco":2,"Abril":1,"Maio":0,"Junho":0,"Julho":0,"Agosto":3,"Setembro":1,"Outubro":1,"Novembro":0,"Dezembro":1,"Total":15},{"Natureza":"HOMIC\u00cdDIO DOLOSO POR ACIDENTE DE TR\u00c2NSITO","Janeiro":0,"Fevereiro":0,"Marco":0,"Abril":0,"Maio":0,"Junho":0,"Julho":0,"Agosto":0,"Setembro":0,"Outubro":0,"Novembro":0,"Dezembro":0,"Total":0},{"Natureza":"N\u00ba DE V\u00cdTIMAS EM HOMIC\u00cdDIO DOLOSO POR ACIDENTE DE TR\u00c2NSITO","Janeiro":0,"Fevereiro":0,"Marco":0,"Abril":0,"Maio":0,"Junho":0,"Julho":0,"Agosto":0,"Setembro":0,"Outubro":0,"Novembro":0,"Dezembro":0,"Total":0},{"Natureza":"HOMIC\u00cdDIO CULPOSO POR ACIDENTE DE TR\u00c2NSITO","Janeiro":1,"Fevereiro":0,"Marco":0,"Abril":2,"Maio":0,"Junho":1,"Julho":0,"Agosto":0,"Setembro":1,"Outubro":0,"Novembro":0,"Dezembro":0,"Total":5},{"Natureza":"HOMIC\u00cdDIO CULPOSO OUTROS","Janeiro":0,"Fevereiro":0,"Marco":0,"Abril":0,"Maio":0,"Junho":0,"Julho":0,"Agosto":0,"Setembro":0,"Outubro":0,"Novembro":0,"Dezembro":0,"Total":0},{"Natureza":"TENTATIVA DE HOMIC\u00cdDIO","Janeiro":0,"Fevereiro":3,"Marco":0,"Abril":1,"Maio":1,"Junho":1,"Julho":1,"Agosto":3,"Setembro":0,"Outubro":0,"Novembro":0,"Dezembro":0,"Total":10},{"Natureza":"LES\u00c3O CORPORAL DOLOSA","Janeiro":36,"Fevereiro":28,"Marco":24,"Abril":18,"Maio":16,"Junho":14,"Julho":9,"Agosto":17,"Setembro":17,"Outubro":21,"Novembro":26,"Dezembro":29,"Total":255},{"Natureza":"LES\u00c3O CORPORAL CULPOSA POR ACIDENTE DE TR\u00c2NSITO","Janeiro":6,"Fevereiro":20,"Marco":28,"Abril":27,"Maio":27,"Junho":24,"Julho":28,"Agosto":24,"Setembro":37,"Outubro":31,"Novembro":21,"Dezembro":15,"Total":288},{"Natureza":"LES\u00c3O CORPORAL CULPOSA - OUTRAS","Janeiro":2,"Fevereiro":3,"Marco":0,"Abril":0,"Maio":0,"Junho":0,"Julho":1,"Agosto":1,"Setembro":1,"Outubro":0,"Novembro":0,"Dezembro":2,"Total":10},{"Natureza":"LATROC\u00cdNIO","Janeiro":0,"Fevereiro":0,"Marco":0,"Abril":0,"Maio":0,"Junho":0,"Julho":1,"Agosto":0,"Setembro":0,"Outubro":0,"Novembro":0,"Dezembro":0,"Total":1},{"Natureza":"N\u00ba DE V\u00cdTIMAS EM LATROC\u00cdNIO","Janeiro":0,"Fevereiro":0,"Marco":0,"Abril":0,"Maio":0,"Junho":0,"Julho":1,"Agosto":0,"Setembro":0,"Outubro":0,"Novembro":0,"Dezembro":0,"Total":1},{"Natureza":"TOTAL DE ESTUPRO (4)","Janeiro":0,"Fevereiro":1,"Marco":3,"Abril":1,"Maio":1,"Junho":1,"Julho":2,"Agosto":2,"Setembro":6,"Outubro":0,"Novembro":0,"Dezembro":0,"Total":17},{"Natureza":"TOTAL DE ROUBO - OUTROS (1)","Janeiro":77,"Fevereiro":50,"Marco":75,"Abril":79,"Maio":59,"Junho":63,"Julho":77,"Agosto":89,"Setembro":77,"Outubro":69,"Novembro":69,"Dezembro":68,"Total":852},{"Natureza":"ROUBO DE VE\u00cdCULO","Janeiro":28,"Fevereiro":33,"Marco":32,"Abril":37,"Maio":26,"Junho":16,"Julho":26,"Agosto":28,"Setembro":21,"Outubro":23,"Novembro":38,"Dezembro":27,"Total":335},{"Natureza":"ROUBO A BANCO","Janeiro":0,"Fevereiro":0,"Marco":0,"Abril":1,"Maio":0,"Junho":0,"Julho":0,"Agosto":0,"Setembro":0,"Outubro":0,"Novembro":0,"Dezembro":0,"Total":1},{"Natureza":"ROUBO DE CARGA","Janeiro":5,"Fevereiro":2,"Marco":5,"Abril":2,"Maio":1,"Junho":3,"Julho":4,"Agosto":0,"Setembro":1,"Outubro":3,"Novembro":5,"Dezembro":5,"Total":36},{"Natureza":"FURTO - OUTROS","Janeiro":66,"Fevereiro":78,"Marco":60,"Abril":44,"Maio":95,"Junho":75,"Julho":67,"Agosto":61,"Setembro":87,"Outubro":58,"Novembro":91,"Dezembro":71,"Total":853},{"Natureza":"FURTO DE VE\u00cdCULO","Janeiro":16,"Fevereiro":28,"Marco":32,"Abril":26,"Maio":39,"Junho":37,"Julho":38,"Agosto":17,"Setembro":39,"Outubro":51,"Novembro":33,"Dezembro":36,"Total":392}]