[{"Natureza":"HOMIC\u00cdDIO DOLOSO (2)","Janeiro":0,"Fevereiro":0,"Marco":0,"Abril":0,"Maio":1,"Junho":1,"Julho":0,"Agosto":0,"Setembro":2,"Outubro":0,"Novembro":1,"Dezembro":0,"Total":5},{"Natureza":"N\u00ba DE V\u00cdTIMAS EM HOMIC\u00cdDIO DOLOSO (3)","Janeiro":0,"Fevereiro":0,"Marco":0,"Abril":0,"Maio":1,"Junho":2,"Julho":0,"Agosto":0,"Setembro":2,"Outubro":0,"Novembro":1,"Dezembro":0,"Total":6},{"Natureza":"HOMIC\u00cdDIO DOLOSO POR ACIDENTE DE TR\u00c2NSITO","Janeiro":0,"Fevereiro":0,"Marco":0,"Abril":0,"Maio":0,"Junho":0,"Julho":0,"Agosto":0,"Setembro":0,"Outubro":0,"Novembro":0,"Dezembro":0,"Total":0},{"Natureza":"N\u00ba DE V\u00cdTIMAS EM HOMIC\u00cdDIO DOLOSO POR ACIDENTE DE TR\u00c2NSITO","Janeiro":0,"Fevereiro":0,"Marco":0,"Abril":0,"Maio":0,"Junho":0,"Julho":0,"Agosto":0,"Setembro":0,"Outubro":0,"Novembro":0,"Dezembro":0,"Total":0},{"Natureza":"HOMIC\u00cdDIO CULPOSO POR ACIDENTE DE TR\u00c2NSITO","Janeiro":0,"Fevereiro":0,"Marco":0,"Abril":0,"Maio":0,"Junho":0,"Julho":0,"Agosto":0,"Setembro":0,"Outubro":1,"Novembro":0,"Dezembro":0,"Total":1},{"Natureza":"HOMIC\u00cdDIO CULPOSO OUTROS","Janeiro":0,"Fevereiro":0,"Marco":0,"Abril":0,"Maio":0,"Junho":0,"Julho":0,"Agosto":0,"Setembro":0,"Outubro":0,"Novembro":0,"Dezembro":0,"Total":0},{"Natureza":"TENTATIVA DE HOMIC\u00cdDIO","Janeiro":3,"Fevereiro":0,"Marco":2,"Abril":0,"Maio":0,"Junho":0,"Julho":0,"Agosto":0,"Setembro":0,"Outubro":0,"Novembro":0,"Dezembro":0,"Total":5},{"Natureza":"LES\u00c3O CORPORAL SEGUIDA DE MORTE","Janeiro":0,"Fevereiro":0,"Marco":0,"Abril":0,"Maio":0,"Junho":0,"Julho":0,"Agosto":0,"Setembro":0,"Outubro":0,"Novembro":0,"Dezembro":0,"Total":0},{"Natureza":"LES\u00c3O CORPORAL DOLOSA","Janeiro":15,"Fevereiro":11,"Marco":14,"Abril":9,"Maio":12,"Junho":11,"Julho":8,"Agosto":7,"Setembro":9,"Outubro":10,"Novembro":12,"Dezembro":9,"Total":127},{"Natureza":"LES\u00c3O CORPORAL CULPOSA POR ACIDENTE DE TR\u00c2NSITO","Janeiro":6,"Fevereiro":8,"Marco":5,"Abril":6,"Maio":5,"Junho":7,"Julho":8,"Agosto":7,"Setembro":7,"Outubro":11,"Novembro":11,"Dezembro":11,"Total":92},{"Natureza":"LES\u00c3O CORPORAL CULPOSA - OUTRAS","Janeiro":0,"Fevereiro":1,"Marco":0,"Abril":1,"Maio":2,"Junho":1,"Julho":3,"Agosto":1,"Setembro":0,"Outubro":3,"Novembro":0,"Dezembro":0,"Total":12},{"Natureza":"LATROC\u00cdNIO","Janeiro":0,"Fevereiro":0,"Marco":0,"Abril":0,"Maio":0,"Junho":0,"Julho":0,"Agosto":0,"Setembro":0,"Outubro":0,"Novembro":1,"Dezembro":0,"Total":1},{"Natureza":"N\u00ba DE V\u00cdTIMAS EM LATROC\u00cdNIO","Janeiro":0,"Fevereiro":0,"Marco":0,"Abril":0,"Maio":0,"Junho":0,"Julho":0,"Agosto":0,"Setembro":0,"Outubro":0,"Novembro":1,"Dezembro":0,"Total":1},{"Natureza":"TOTAL DE ESTUPRO (4)","Janeiro":0,"Fevereiro":0,"Marco":0,"Abril":0,"Maio":0,"Junho":0,"Julho":0,"Agosto":0,"Setembro":0,"Outubro":0,"Novembro":0,"Dezembro":0,"Total":0},{"Natureza":"TOTAL DE ROUBO - OUTROS (1)","Janeiro":37,"Fevereiro":35,"Marco":26,"Abril":30,"Maio":44,"Junho":40,"Julho":32,"Agosto":29,"Setembro":40,"Outubro":32,"Novembro":29,"Dezembro":33,"Total":407},{"Natureza":"ROUBO DE VE\u00cdCULO","Janeiro":7,"Fevereiro":10,"Marco":4,"Abril":19,"Maio":18,"Junho":13,"Julho":27,"Agosto":11,"Setembro":11,"Outubro":4,"Novembro":11,"Dezembro":3,"Total":138},{"Natureza":"ROUBO A BANCO","Janeiro":2,"Fevereiro":0,"Marco":0,"Abril":0,"Maio":0,"Junho":0,"Julho":0,"Agosto":0,"Setembro":0,"Outubro":0,"Novembro":0,"Dezembro":0,"Total":2},{"Natureza":"ROUBO DE CARGA","Janeiro":5,"Fevereiro":1,"Marco":1,"Abril":1,"Maio":2,"Junho":0,"Julho":1,"Agosto":1,"Setembro":1,"Outubro":0,"Novembro":0,"Dezembro":1,"Total":14},{"Natureza":"FURTO - OUTROS","Janeiro":44,"Fevereiro":45,"Marco":42,"Abril":39,"Maio":30,"Junho":63,"Julho":52,"Agosto":44,"Setembro":55,"Outubro":53,"Novembro":99,"Dezembro":45,"Total":611},{"Natureza":"FURTO DE VE\u00cdCULO","Janeiro":32,"Fevereiro":29,"Marco":31,"Abril":33,"Maio":31,"Junho":30,"Julho":26,"Agosto":19,"Setembro":30,"Outubro":32,"Novembro":25,"Dezembro":21,"Total":339}]