[{"Natureza":"HOMIC\u00cdDIO DOLOSO (2)","Janeiro":0,"Fevereiro":1,"Marco":0,"Abril":2,"Maio":1,"Junho":0,"Julho":0,"Agosto":1,"Setembro":0,"Outubro":2,"Novembro":0,"Dezembro":0,"Total":7.0},{"Natureza":"N\u00ba DE V\u00cdTIMAS EM HOMIC\u00cdDIO DOLOSO (3)","Janeiro":0,"Fevereiro":1,"Marco":0,"Abril":2,"Maio":1,"Junho":0,"Julho":0,"Agosto":1,"Setembro":0,"Outubro":2,"Novembro":0,"Dezembro":0,"Total":7.0},{"Natureza":"HOMIC\u00cdDIO DOLOSO POR ACIDENTE DE TR\u00c2NSITO","Janeiro":0,"Fevereiro":0,"Marco":0,"Abril":0,"Maio":0,"Junho":0,"Julho":0,"Agosto":0,"Setembro":0,"Outubro":0,"Novembro":0,"Dezembro":0,"Total":0.0},{"Natureza":"N\u00ba DE V\u00cdTIMAS EM HOMIC\u00cdDIO DOLOSO POR ACIDENTE DE TR\u00c2NSITO","Janeiro":0,"Fevereiro":0,"Marco":0,"Abril":0,"Maio":0,"Junho":0,"Julho":0,"Agosto":0,"Setembro":0,"Outubro":0,"Novembro":0,"Dezembro":0,"Total":0.0},{"Natureza":"HOMIC\u00cdDIO CULPOSO POR ACIDENTE DE TR\u00c2NSITO","Janeiro":0,"Fevereiro":1,"Marco":0,"Abril":0,"Maio":1,"Junho":1,"Julho":0,"Agosto":0,"Setembro":0,"Outubro":0,"Novembro":0,"Dezembro":0,"Total":3.0},{"Natureza":"HOMIC\u00cdDIO CULPOSO OUTROS","Janeiro":0,"Fevereiro":0,"Marco":0,"Abril":0,"Maio":0,"Junho":0,"Julho":0,"Agosto":0,"Setembro":0,"Outubro":0,"Novembro":0,"Dezembro":0,"Total":0.0},{"Natureza":"TENTATIVA DE HOMIC\u00cdDIO","Janeiro":0,"Fevereiro":0,"Marco":1,"Abril":1,"Maio":0,"Junho":0,"Julho":0,"Agosto":0,"Setembro":0,"Outubro":1,"Novembro":0,"Dezembro":0,"Total":3.0},{"Natureza":"LES\u00c3O CORPORAL SEGUIDA DE MORTE","Janeiro":0,"Fevereiro":0,"Marco":0,"Abril":0,"Maio":0,"Junho":0,"Julho":0,"Agosto":0,"Setembro":0,"Outubro":0,"Novembro":0,"Dezembro":0,"Total":0.0},{"Natureza":"LES\u00c3O CORPORAL DOLOSA","Janeiro":23,"Fevereiro":21,"Marco":15,"Abril":13,"Maio":14,"Junho":11,"Julho":18,"Agosto":17,"Setembro":14,"Outubro":11,"Novembro":4,"Dezembro":13,"Total":174.0},{"Natureza":"LES\u00c3O CORPORAL CULPOSA POR ACIDENTE DE TR\u00c2NSITO","Janeiro":4,"Fevereiro":2,"Marco":2,"Abril":2,"Maio":2,"Junho":3,"Julho":6,"Agosto":1,"Setembro":2,"Outubro":1,"Novembro":4,"Dezembro":5,"Total":34.0},{"Natureza":"LES\u00c3O CORPORAL CULPOSA - OUTRAS","Janeiro":0,"Fevereiro":1,"Marco":0,"Abril":1,"Maio":1,"Junho":1,"Julho":0,"Agosto":0,"Setembro":0,"Outubro":0,"Novembro":1,"Dezembro":0,"Total":5.0},{"Natureza":"LATROC\u00cdNIO","Janeiro":0,"Fevereiro":0,"Marco":0,"Abril":0,"Maio":0,"Junho":0,"Julho":0,"Agosto":0,"Setembro":0,"Outubro":0,"Novembro":0,"Dezembro":0,"Total":0.0},{"Natureza":"N\u00ba DE V\u00cdTIMAS EM LATROC\u00cdNIO","Janeiro":0,"Fevereiro":0,"Marco":0,"Abril":0,"Maio":0,"Junho":0,"Julho":0,"Agosto":0,"Setembro":0,"Outubro":0,"Novembro":0,"Dezembro":0,"Total":0.0},{"Natureza":"TOTAL DE ESTUPRO (4)","Janeiro":3,"Fevereiro":1,"Marco":0,"Abril":1,"Maio":0,"Junho":0,"Julho":0,"Agosto":0,"Setembro":0,"Outubro":2,"Novembro":0,"Dezembro":1,"Total":8.0},{"Natureza":"ESTUPRO","Janeiro":0,"Fevereiro":1,"Marco":0,"Abril":1,"Maio":0,"Junho":0,"Julho":0,"Agosto":0,"Setembro":0,"Outubro":1,"Novembro":0,"Dezembro":0,"Total":3.0},{"Natureza":"ESTUPRO DE VULNER\u00c1VEL","Janeiro":3,"Fevereiro":0,"Marco":0,"Abril":0,"Maio":0,"Junho":0,"Julho":0,"Agosto":0,"Setembro":0,"Outubro":1,"Novembro":0,"Dezembro":1,"Total":5.0},{"Natureza":"TOTAL DE ROUBO - OUTROS (1)","Janeiro":125,"Fevereiro":128,"Marco":95,"Abril":93,"Maio":89,"Junho":109,"Julho":115,"Agosto":109,"Setembro":118,"Outubro":116,"Novembro":115,"Dezembro":111,"Total":1323.0},{"Natureza":"ROUBO - OUTROS","Janeiro":125,"Fevereiro":127,"Marco":94,"Abril":92,"Maio":89,"Junho":106,"Julho":113,"Agosto":109,"Setembro":118,"Outubro":116,"Novembro":115,"Dezembro":111,"Total":1315.0},{"Natureza":"ROUBO DE VE\u00cdCULO","Janeiro":2,"Fevereiro":1,"Marco":0,"Abril":2,"Maio":2,"Junho":1,"Julho":1,"Agosto":1,"Setembro":2,"Outubro":1,"Novembro":4,"Dezembro":0,"Total":17.0},{"Natureza":"ROUBO A BANCO","Janeiro":0,"Fevereiro":0,"Marco":0,"Abril":0,"Maio":0,"Junho":0,"Julho":0,"Agosto":0,"Setembro":0,"Outubro":0,"Novembro":0,"Dezembro":0,"Total":0.0},{"Natureza":"ROUBO DE CARGA","Janeiro":0,"Fevereiro":1,"Marco":1,"Abril":1,"Maio":0,"Junho":3,"Julho":2,"Agosto":0,"Setembro":0,"Outubro":0,"Novembro":0,"Dezembro":0,"Total":8.0},{"Natureza":"FURTO - OUTROS","Janeiro":316,"Fevereiro":308,"Marco":263,"Abril":263,"Maio":316,"Junho":305,"Julho":322,"Agosto":357,"Setembro":379,"Outubro":325,"Novembro":397,"Dezembro":357,"Total":3908.0},{"Natureza":"FURTO DE VE\u00cdCULO","Janeiro":7,"Fevereiro":17,"Marco":15,"Abril":11,"Maio":7,"Junho":15,"Julho":9,"Agosto":20,"Setembro":14,"Outubro":15,"Novembro":11,"Dezembro":15,"Total":156.0}]