[{"Natureza":"HOMIC\u00cdDIO DOLOSO (2)","Janeiro":2,"Fevereiro":1,"Marco":3,"Abril":4,"Maio":1,"Junho":0,"Julho":2,"Agosto":2,"Setembro":1,"Outubro":0,"Novembro":1,"Dezembro":1,"Total":18.0},{"Natureza":"N\u00ba DE V\u00cdTIMAS EM HOMIC\u00cdDIO DOLOSO (3)","Janeiro":2,"Fevereiro":1,"Marco":3,"Abril":4,"Maio":1,"Junho":0,"Julho":2,"Agosto":2,"Setembro":1,"Outubro":0,"Novembro":1,"Dezembro":1,"Total":18.0},{"Natureza":"HOMIC\u00cdDIO DOLOSO POR ACIDENTE DE TR\u00c2NSITO","Janeiro":0,"Fevereiro":0,"Marco":0,"Abril":0,"Maio":0,"Junho":0,"Julho":0,"Agosto":0,"Setembro":0,"Outubro":0,"Novembro":0,"Dezembro":0,"Total":0.0},{"Natureza":"N\u00ba DE V\u00cdTIMAS EM HOMIC\u00cdDIO DOLOSO POR ACIDENTE DE TR\u00c2NSITO","Janeiro":0,"Fevereiro":0,"Marco":0,"Abril":0,"Maio":0,"Junho":0,"Julho":0,"Agosto":0,"Setembro":0,"Outubro":0,"Novembro":0,"Dezembro":0,"Total":0.0},{"Natureza":"HOMIC\u00cdDIO CULPOSO POR ACIDENTE DE TR\u00c2NSITO","Janeiro":1,"Fevereiro":0,"Marco":3,"Abril":2,"Maio":0,"Junho":3,"Julho":0,"Agosto":1,"Setembro":1,"Outubro":0,"Novembro":4,"Dezembro":0,"Total":15.0},{"Natureza":"HOMIC\u00cdDIO CULPOSO OUTROS","Janeiro":0,"Fevereiro":0,"Marco":0,"Abril":0,"Maio":0,"Junho":0,"Julho":0,"Agosto":0,"Setembro":0,"Outubro":0,"Novembro":0,"Dezembro":0,"Total":0.0},{"Natureza":"TENTATIVA DE HOMIC\u00cdDIO","Janeiro":1,"Fevereiro":2,"Marco":4,"Abril":2,"Maio":2,"Junho":2,"Julho":1,"Agosto":0,"Setembro":1,"Outubro":0,"Novembro":2,"Dezembro":3,"Total":20.0},{"Natureza":"LES\u00c3O CORPORAL SEGUIDA DE MORTE","Janeiro":0,"Fevereiro":0,"Marco":0,"Abril":0,"Maio":0,"Junho":0,"Julho":0,"Agosto":0,"Setembro":0,"Outubro":0,"Novembro":0,"Dezembro":0,"Total":0.0},{"Natureza":"LES\u00c3O CORPORAL DOLOSA","Janeiro":36,"Fevereiro":49,"Marco":44,"Abril":33,"Maio":18,"Junho":18,"Julho":19,"Agosto":24,"Setembro":30,"Outubro":20,"Novembro":27,"Dezembro":30,"Total":348.0},{"Natureza":"LES\u00c3O CORPORAL CULPOSA POR ACIDENTE DE TR\u00c2NSITO","Janeiro":30,"Fevereiro":34,"Marco":42,"Abril":24,"Maio":28,"Junho":25,"Julho":27,"Agosto":30,"Setembro":28,"Outubro":22,"Novembro":24,"Dezembro":23,"Total":337.0},{"Natureza":"LES\u00c3O CORPORAL CULPOSA - OUTRAS","Janeiro":0,"Fevereiro":0,"Marco":0,"Abril":0,"Maio":0,"Junho":0,"Julho":0,"Agosto":0,"Setembro":0,"Outubro":0,"Novembro":0,"Dezembro":0,"Total":0.0},{"Natureza":"LATROC\u00cdNIO","Janeiro":0,"Fevereiro":0,"Marco":0,"Abril":0,"Maio":0,"Junho":0,"Julho":0,"Agosto":0,"Setembro":0,"Outubro":0,"Novembro":0,"Dezembro":0,"Total":0.0},{"Natureza":"N\u00ba DE V\u00cdTIMAS EM LATROC\u00cdNIO","Janeiro":0,"Fevereiro":0,"Marco":0,"Abril":0,"Maio":1,"Junho":0,"Julho":0,"Agosto":0,"Setembro":0,"Outubro":0,"Novembro":0,"Dezembro":0,"Total":1.0},{"Natureza":"TOTAL DE ESTUPRO (4)","Janeiro":2,"Fevereiro":0,"Marco":1,"Abril":0,"Maio":0,"Junho":0,"Julho":2,"Agosto":0,"Setembro":0,"Outubro":1,"Novembro":0,"Dezembro":0,"Total":6.0},{"Natureza":"TOTAL DE ROUBO - OUTROS (1)","Janeiro":138,"Fevereiro":172,"Marco":160,"Abril":133,"Maio":100,"Junho":109,"Julho":126,"Agosto":108,"Setembro":106,"Outubro":102,"Novembro":93,"Dezembro":90,"Total":1.437},{"Natureza":"ROUBO DE VE\u00cdCULO","Janeiro":120,"Fevereiro":101,"Marco":108,"Abril":94,"Maio":88,"Junho":103,"Julho":108,"Agosto":120,"Setembro":79,"Outubro":72,"Novembro":49,"Dezembro":48,"Total":1.09},{"Natureza":"ROUBO A BANCO","Janeiro":0,"Fevereiro":0,"Marco":0,"Abril":0,"Maio":0,"Junho":0,"Julho":0,"Agosto":0,"Setembro":0,"Outubro":0,"Novembro":0,"Dezembro":0,"Total":0.0},{"Natureza":"ROUBO DE CARGA","Janeiro":2,"Fevereiro":6,"Marco":2,"Abril":4,"Maio":2,"Junho":0,"Julho":0,"Agosto":0,"Setembro":2,"Outubro":3,"Novembro":0,"Dezembro":2,"Total":23.0},{"Natureza":"FURTO - OUTROS","Janeiro":76,"Fevereiro":73,"Marco":82,"Abril":86,"Maio":99,"Junho":73,"Julho":84,"Agosto":82,"Setembro":84,"Outubro":73,"Novembro":73,"Dezembro":80,"Total":965.0},{"Natureza":"FURTO DE VE\u00cdCULO","Janeiro":23,"Fevereiro":28,"Marco":30,"Abril":35,"Maio":31,"Junho":20,"Julho":26,"Agosto":26,"Setembro":23,"Outubro":19,"Novembro":17,"Dezembro":9,"Total":287.0}]