[{"Natureza":"HOMIC\u00cdDIO DOLOSO (2)","Janeiro":6,"Fevereiro":1,"Marco":6,"Abril":5,"Maio":4,"Junho":3,"Julho":2,"Agosto":2,"Setembro":2,"Outubro":6,"Novembro":3,"Dezembro":1,"Total":41},{"Natureza":"N\u00ba DE V\u00cdTIMAS EM HOMIC\u00cdDIO DOLOSO (3)","Janeiro":7,"Fevereiro":1,"Marco":7,"Abril":5,"Maio":5,"Junho":3,"Julho":2,"Agosto":2,"Setembro":2,"Outubro":7,"Novembro":4,"Dezembro":2,"Total":47},{"Natureza":"HOMIC\u00cdDIO DOLOSO POR ACIDENTE DE TR\u00c2NSITO","Janeiro":0,"Fevereiro":0,"Marco":0,"Abril":0,"Maio":0,"Junho":0,"Julho":0,"Agosto":0,"Setembro":1,"Outubro":0,"Novembro":0,"Dezembro":0,"Total":1},{"Natureza":"N\u00ba DE V\u00cdTIMAS EM HOMIC\u00cdDIO DOLOSO POR ACIDENTE DE TR\u00c2NSITO","Janeiro":0,"Fevereiro":0,"Marco":0,"Abril":0,"Maio":0,"Junho":0,"Julho":0,"Agosto":0,"Setembro":1,"Outubro":0,"Novembro":0,"Dezembro":0,"Total":1},{"Natureza":"HOMIC\u00cdDIO CULPOSO POR ACIDENTE DE TR\u00c2NSITO","Janeiro":0,"Fevereiro":0,"Marco":0,"Abril":0,"Maio":8,"Junho":0,"Julho":1,"Agosto":0,"Setembro":1,"Outubro":1,"Novembro":0,"Dezembro":0,"Total":11},{"Natureza":"HOMIC\u00cdDIO CULPOSO OUTROS","Janeiro":0,"Fevereiro":0,"Marco":0,"Abril":0,"Maio":0,"Junho":0,"Julho":0,"Agosto":0,"Setembro":0,"Outubro":0,"Novembro":0,"Dezembro":0,"Total":0},{"Natureza":"TENTATIVA DE HOMIC\u00cdDIO","Janeiro":3,"Fevereiro":1,"Marco":2,"Abril":2,"Maio":1,"Junho":4,"Julho":0,"Agosto":7,"Setembro":1,"Outubro":2,"Novembro":3,"Dezembro":3,"Total":29},{"Natureza":"LES\u00c3O CORPORAL DOLOSA","Janeiro":23,"Fevereiro":31,"Marco":22,"Abril":11,"Maio":22,"Junho":21,"Julho":18,"Agosto":13,"Setembro":28,"Outubro":23,"Novembro":19,"Dezembro":21,"Total":252},{"Natureza":"LES\u00c3O CORPORAL CULPOSA POR ACIDENTE DE TR\u00c2NSITO","Janeiro":9,"Fevereiro":18,"Marco":18,"Abril":14,"Maio":15,"Junho":29,"Julho":14,"Agosto":12,"Setembro":26,"Outubro":19,"Novembro":6,"Dezembro":30,"Total":210},{"Natureza":"LES\u00c3O CORPORAL CULPOSA - OUTRAS","Janeiro":0,"Fevereiro":2,"Marco":0,"Abril":0,"Maio":0,"Junho":10,"Julho":0,"Agosto":0,"Setembro":4,"Outubro":4,"Novembro":4,"Dezembro":0,"Total":24},{"Natureza":"LATROC\u00cdNIO","Janeiro":1,"Fevereiro":0,"Marco":0,"Abril":0,"Maio":1,"Junho":0,"Julho":0,"Agosto":0,"Setembro":0,"Outubro":1,"Novembro":0,"Dezembro":0,"Total":3},{"Natureza":"N\u00ba DE V\u00cdTIMAS EM LATROC\u00cdNIO","Janeiro":1,"Fevereiro":0,"Marco":0,"Abril":0,"Maio":2,"Junho":0,"Julho":0,"Agosto":0,"Setembro":0,"Outubro":1,"Novembro":0,"Dezembro":0,"Total":4},{"Natureza":"TOTAL DE ESTUPRO (4)","Janeiro":2,"Fevereiro":5,"Marco":2,"Abril":6,"Maio":13,"Junho":4,"Julho":1,"Agosto":7,"Setembro":4,"Outubro":3,"Novembro":1,"Dezembro":4,"Total":52},{"Natureza":"TOTAL DE ROUBO - OUTROS (1)","Janeiro":71,"Fevereiro":76,"Marco":86,"Abril":74,"Maio":64,"Junho":86,"Julho":77,"Agosto":67,"Setembro":90,"Outubro":93,"Novembro":86,"Dezembro":63,"Total":933},{"Natureza":"ROUBO DE VE\u00cdCULO","Janeiro":24,"Fevereiro":17,"Marco":19,"Abril":15,"Maio":32,"Junho":24,"Julho":11,"Agosto":17,"Setembro":29,"Outubro":18,"Novembro":15,"Dezembro":35,"Total":256},{"Natureza":"ROUBO A BANCO","Janeiro":0,"Fevereiro":0,"Marco":0,"Abril":0,"Maio":0,"Junho":0,"Julho":0,"Agosto":0,"Setembro":0,"Outubro":0,"Novembro":1,"Dezembro":0,"Total":1},{"Natureza":"ROUBO DE CARGA","Janeiro":0,"Fevereiro":0,"Marco":0,"Abril":0,"Maio":0,"Junho":2,"Julho":0,"Agosto":0,"Setembro":0,"Outubro":1,"Novembro":0,"Dezembro":3,"Total":6},{"Natureza":"FURTO - OUTROS","Janeiro":75,"Fevereiro":57,"Marco":73,"Abril":77,"Maio":52,"Junho":52,"Julho":47,"Agosto":73,"Setembro":94,"Outubro":76,"Novembro":64,"Dezembro":85,"Total":825},{"Natureza":"FURTO DE VE\u00cdCULO","Janeiro":15,"Fevereiro":7,"Marco":13,"Abril":5,"Maio":9,"Junho":12,"Julho":12,"Agosto":15,"Setembro":15,"Outubro":8,"Novembro":7,"Dezembro":13,"Total":131}]