[{"Natureza":"HOMIC\u00cdDIO DOLOSO (2)","Janeiro":0,"Fevereiro":0,"Marco":0,"Abril":0,"Maio":0,"Junho":0,"Julho":0,"Agosto":1,"Setembro":2,"Outubro":0,"Novembro":0,"Dezembro":0,"Total":3.0},{"Natureza":"N\u00ba DE V\u00cdTIMAS EM HOMIC\u00cdDIO DOLOSO (3)","Janeiro":0,"Fevereiro":0,"Marco":0,"Abril":0,"Maio":0,"Junho":0,"Julho":0,"Agosto":1,"Setembro":2,"Outubro":0,"Novembro":0,"Dezembro":0,"Total":3.0},{"Natureza":"HOMIC\u00cdDIO DOLOSO POR ACIDENTE DE TR\u00c2NSITO","Janeiro":0,"Fevereiro":0,"Marco":0,"Abril":0,"Maio":0,"Junho":0,"Julho":0,"Agosto":0,"Setembro":0,"Outubro":0,"Novembro":0,"Dezembro":0,"Total":0.0},{"Natureza":"N\u00ba DE V\u00cdTIMAS EM HOMIC\u00cdDIO DOLOSO POR ACIDENTE DE TR\u00c2NSITO","Janeiro":0,"Fevereiro":0,"Marco":0,"Abril":0,"Maio":0,"Junho":0,"Julho":0,"Agosto":0,"Setembro":0,"Outubro":0,"Novembro":0,"Dezembro":0,"Total":0.0},{"Natureza":"HOMIC\u00cdDIO CULPOSO POR ACIDENTE DE TR\u00c2NSITO","Janeiro":0,"Fevereiro":0,"Marco":0,"Abril":1,"Maio":1,"Junho":0,"Julho":0,"Agosto":0,"Setembro":0,"Outubro":0,"Novembro":0,"Dezembro":0,"Total":2.0},{"Natureza":"HOMIC\u00cdDIO CULPOSO OUTROS","Janeiro":0,"Fevereiro":0,"Marco":0,"Abril":0,"Maio":0,"Junho":0,"Julho":0,"Agosto":0,"Setembro":0,"Outubro":0,"Novembro":0,"Dezembro":0,"Total":0.0},{"Natureza":"TENTATIVA DE HOMIC\u00cdDIO","Janeiro":0,"Fevereiro":0,"Marco":1,"Abril":0,"Maio":0,"Junho":0,"Julho":0,"Agosto":1,"Setembro":1,"Outubro":0,"Novembro":0,"Dezembro":0,"Total":3.0},{"Natureza":"LES\u00c3O CORPORAL SEGUIDA DE MORTE","Janeiro":0,"Fevereiro":0,"Marco":0,"Abril":0,"Maio":0,"Junho":0,"Julho":0,"Agosto":0,"Setembro":0,"Outubro":0,"Novembro":0,"Dezembro":0,"Total":0.0},{"Natureza":"LES\u00c3O CORPORAL DOLOSA","Janeiro":25,"Fevereiro":25,"Marco":24,"Abril":24,"Maio":22,"Junho":31,"Julho":25,"Agosto":17,"Setembro":20,"Outubro":18,"Novembro":21,"Dezembro":29,"Total":281.0},{"Natureza":"LES\u00c3O CORPORAL CULPOSA POR ACIDENTE DE TR\u00c2NSITO","Janeiro":22,"Fevereiro":24,"Marco":20,"Abril":17,"Maio":16,"Junho":21,"Julho":18,"Agosto":10,"Setembro":22,"Outubro":14,"Novembro":16,"Dezembro":9,"Total":209.0},{"Natureza":"LES\u00c3O CORPORAL CULPOSA - OUTRAS","Janeiro":4,"Fevereiro":3,"Marco":2,"Abril":0,"Maio":0,"Junho":1,"Julho":1,"Agosto":1,"Setembro":1,"Outubro":1,"Novembro":0,"Dezembro":1,"Total":15.0},{"Natureza":"LATROC\u00cdNIO","Janeiro":0,"Fevereiro":0,"Marco":0,"Abril":0,"Maio":0,"Junho":0,"Julho":0,"Agosto":0,"Setembro":0,"Outubro":0,"Novembro":0,"Dezembro":0,"Total":0.0},{"Natureza":"N\u00ba DE V\u00cdTIMAS EM LATROC\u00cdNIO","Janeiro":0,"Fevereiro":0,"Marco":0,"Abril":0,"Maio":0,"Junho":0,"Julho":0,"Agosto":0,"Setembro":0,"Outubro":0,"Novembro":0,"Dezembro":0,"Total":0.0},{"Natureza":"TOTAL DE ESTUPRO (4)","Janeiro":1,"Fevereiro":2,"Marco":2,"Abril":3,"Maio":0,"Junho":0,"Julho":1,"Agosto":3,"Setembro":1,"Outubro":2,"Novembro":2,"Dezembro":1,"Total":18.0},{"Natureza":"ESTUPRO DE VULNER\u00c1VEL","Janeiro":0,"Fevereiro":0,"Marco":0,"Abril":0,"Maio":0,"Junho":0,"Julho":0,"Agosto":0,"Setembro":0,"Outubro":0,"Novembro":0,"Dezembro":0,"Total":0.0},{"Natureza":"TOTAL DE ROUBO - OUTROS (1)","Janeiro":68,"Fevereiro":68,"Marco":106,"Abril":103,"Maio":83,"Junho":102,"Julho":84,"Agosto":81,"Setembro":96,"Outubro":105,"Novembro":87,"Dezembro":69,"Total":1052.0},{"Natureza":"ROUBO DE VE\u00cdCULO","Janeiro":22,"Fevereiro":23,"Marco":31,"Abril":41,"Maio":35,"Junho":30,"Julho":19,"Agosto":24,"Setembro":16,"Outubro":23,"Novembro":23,"Dezembro":18,"Total":305.0},{"Natureza":"ROUBO A BANCO","Janeiro":0,"Fevereiro":0,"Marco":0,"Abril":0,"Maio":0,"Junho":0,"Julho":0,"Agosto":0,"Setembro":0,"Outubro":0,"Novembro":1,"Dezembro":0,"Total":1.0},{"Natureza":"ROUBO DE CARGA","Janeiro":7,"Fevereiro":1,"Marco":1,"Abril":2,"Maio":1,"Junho":2,"Julho":1,"Agosto":3,"Setembro":1,"Outubro":1,"Novembro":1,"Dezembro":1,"Total":22.0},{"Natureza":"FURTO - OUTROS","Janeiro":208,"Fevereiro":189,"Marco":225,"Abril":236,"Maio":234,"Junho":226,"Julho":236,"Agosto":225,"Setembro":244,"Outubro":216,"Novembro":234,"Dezembro":204,"Total":2677.0},{"Natureza":"FURTO DE VE\u00cdCULO","Janeiro":64,"Fevereiro":75,"Marco":80,"Abril":76,"Maio":55,"Junho":59,"Julho":51,"Agosto":69,"Setembro":66,"Outubro":73,"Novembro":78,"Dezembro":58,"Total":804.0}]